Neurocore/__init__.py
Neurocore/include/datasetsBehaviour/DataLoader.h
Neurocore/include/datasetsBehaviour/ImagePreProcessing.cuh
Neurocore/include/examples/Mnist.h
Neurocore/include/examples/Quickdraw.h
Neurocore/include/examples/Tools.h
Neurocore/include/gpuComputation/CUDA.cuh
Neurocore/include/matrix/Matrix.cuh
Neurocore/include/matrix/MatrixGpu.cuh
Neurocore/include/matrix/MatrixPy.hpp
Neurocore/include/matrix/OptimizedMatrix.h
Neurocore/include/matrix/SpecialMatrix.h
Neurocore/include/network/Allocator.h
Neurocore/include/network/InitFunc.cuh
Neurocore/include/network/LayerShape.cuh
Neurocore/include/network/Network.h
Neurocore/include/network/Operations.h
Neurocore/include/network/activation/Activation.cuh
Neurocore/include/network/activation/LeakyReLU.h
Neurocore/include/network/activation/ReLU.h
Neurocore/include/network/activation/Sigmoid.h
Neurocore/include/network/activation/SigmoidPrime.h
Neurocore/include/network/activation/Softmax.h
Neurocore/include/network/activation/Tanh.h
Neurocore/include/network/layers/AveragePooling.cuh
Neurocore/include/network/layers/ConvLayer.cuh
Neurocore/include/network/layers/DropoutFCL.cuh
Neurocore/include/network/layers/FCL.cuh
Neurocore/include/network/layers/InputLayer.cuh
Neurocore/include/network/layers/Layer.cuh
Neurocore/include/network/layers/MaxPooling.cuh
Neurocore/include/network/layers/PoolingLayer.cuh
Neurocore/include/network/layers/Reshape.cuh
Neurocore/include/network/loss/CrossEntropy.cuh
Neurocore/include/network/loss/Loss.h
Neurocore/include/network/loss/MSE.cuh
Neurocore/include/network/optimizers/Adam.h
Neurocore/include/network/optimizers/Constant.h
Neurocore/include/network/optimizers/Optimizer.h
Neurocore/include/pythonWrapper/Activations.hpp
Neurocore/include/pythonWrapper/DataLoader.hpp
Neurocore/include/pythonWrapper/Layers.hpp
Neurocore/include/pythonWrapper/Loss.hpp
Neurocore/include/pythonWrapper/Matrix.hpp
Neurocore/include/pythonWrapper/Opti.hpp
Neurocore/include/tests/ActivationTests.h
neurocore-0.0.1.dist-info/METADATA
neurocore-0.0.1.dist-info/WHEEL
neurocore-0.0.1.dist-info/top_level.txt
neurocore-0.0.1.dist-info/RECORD
